torchprism/PRISM.py
torchprism/__init__.py
torchprism-2.0.0.dist-info/LICENSE
torchprism-2.0.0.dist-info/METADATA
torchprism-2.0.0.dist-info/WHEEL
torchprism-2.0.0.dist-info/top_level.txt
torchprism-2.0.0.dist-info/RECORD
