Metadata-Version: 2.1
Name: torchprism
Version: 2.0.0
Summary: Principal Image Sections Mapping for PyTorch
Home-page: https://github.com/szandala/TorchPRISM
Author: Tomasz Szandala
Author-email: tomasz.szandala@gmail.com
Keywords: deep-learning,PCA,visualization,interpretability
Classifier: Programming Language :: Python :: 3
Classifier: License :: OSI Approved :: MIT License
Classifier: Operating System :: OS Independent
Requires-Python: >=3.6
License-File: LICENSE
Requires-Dist: torch (>=1.1)
Requires-Dist: torchvision (>=0.3.0)
